nonebot_plugin_md-0.2.0.dist-info/METADATA
nonebot_plugin_md-0.2.0.dist-info/WHEEL
nonebot_plugin_md-0.2.0.dist-info/entry_points.txt
nonebot_plugin_md-0.2.0.dist-info/licenses/LICENSE
nonebot_plugin_md/__init__.py
nonebot_plugin_md/__main__.py
nonebot_plugin_md/b30.py
nonebot_plugin_md/config.py
nonebot_plugin_md/message.py
nonebot_plugin_md/model.py
nonebot_plugin_md/template/b30.html
nonebot_plugin_md/utils.py
nonebot_plugin_md-0.2.0.dist-info/RECORD
