Metadata-Version: 2.1
Name: nonebot_plugin_md
Version: 0.2.0
Summary: muse dash for nonebot2
Keywords: md,nonebot2,plugin
Author-Email: Agnes Digital <Z735803792@163.com>
License: AGPL-3.0
Classifier: License :: OSI Approved :: MIT License
Classifier: Programming Language :: Python
Classifier: Programming Language :: Python :: 3
Classifier: Programming Language :: Python :: 3.9
Classifier: Programming Language :: Python :: 3.10
Classifier: Programming Language :: Python :: 3.11
Classifier: Operating System :: OS Independent
Project-URL: homepage, https://github.com/Agnes4m/nonebot_plugin_md
Requires-Python: >=3.9
Requires-Dist: nonebot2>=2.1.1
Requires-Dist: nonebot-plugin-alconna>=0.58.5
Requires-Dist: nonebot_plugin_htmlrender>=0.6.3
Requires-Dist: aiohttp>=3.8.1
Requires-Dist: fuzzywuzzy>=0.18.0
Requires-Dist: lxml>=4.9.1
Requires-Dist: aiofiles>=24.1.0
